gpgLabs/__init__.py
gpgLabs/DC/__init__.py
gpgLabs/EM/FEM3loop.py
gpgLabs/EM/FEMpipe.py
gpgLabs/EM/ResponseFct.py
gpgLabs/EM/__init__.py
gpgLabs/GPR/Attenuation.py
gpgLabs/GPR/GPR_zero_offset.py
gpgLabs/GPR/GPRlab1.py
gpgLabs/GPR/Wiggle.py
gpgLabs/GPR/__init__.py
gpgLabs/Mag/Mag.py
gpgLabs/Mag/MagDipole.py
gpgLabs/Mag/MagUtils.py
gpgLabs/Mag/Simulator.py
gpgLabs/Mag/__init__.py
gpgLabs/Seismic/NMOwidget.py
gpgLabs/Seismic/SeismicRefraction.py
gpgLabs/Seismic/__init__.py
gpgLabs/Seismic/drawGaussianSeismogram.py
gpgLabs/Seismic/syntheticSeismogram.py
gpgLabs-0.0.9.dist-info/DESCRIPTION.rst
gpgLabs-0.0.9.dist-info/METADATA
gpgLabs-0.0.9.dist-info/RECORD
gpgLabs-0.0.9.dist-info/WHEEL
gpgLabs-0.0.9.dist-info/metadata.json
gpgLabs-0.0.9.dist-info/top_level.txt
