Metadata-Version: 2.0
Name: gpgLabs
Version: 0.0.9
Summary: gpgLabs
Home-page: http://gpg.geosci.xyz
Author: GeoSci Developers
Author-email: lheagy@eos.ubc.ca
License: MIT License
Download-URL: https://github.com/geoscixyz/gpgLabs
Keywords: geophysics,electromagnetics
Platform: Windows
Platform: Linux
Platform: Solaris
Platform: Mac OS-X
Platform: Unix
Classifier: Development Status :: 4 - Beta
Classifier: Intended Audience :: Education
Classifier: Intended Audience :: Science/Research
Classifier: License :: OSI Approved :: MIT License
Classifier: Programming Language :: Python
Classifier: Topic :: Scientific/Engineering
Classifier: Topic :: Scientific/Engineering :: Mathematics
Classifier: Topic :: Scientific/Engineering :: Physics
Classifier: Operating System :: Microsoft :: Windows
Classifier: Operating System :: POSIX
Classifier: Operating System :: Unix
Classifier: Operating System :: MacOS
Classifier: Natural Language :: English
Requires-Dist: SimPEG (>=0.4.1)
Requires-Dist: em-examples
Requires-Dist: ipywidgets
Requires-Dist: matplotlib
Requires-Dist: numpy (>=1.7)
Requires-Dist: scipy (>=0.13)
